thealgorithm/__init__.py
thealgorithm/cosine_similarity.py
thealgorithm/discrimination_index.py
thealgorithm/edit_distance.py
thealgorithm/pegasos.py
thealgorithm/abc/__init__.py
thealgorithm/abc/iter.py
thealgorithm/abc/list.py
thealgorithm/abc/priority_queue.py
thealgorithm/abc/stack.py
thealgorithm/abc/tree.py
thealgorithm/data_compression/__init__.py
thealgorithm/data_compression/huffman.py
thealgorithm/data_compression/rle.py
thealgorithm/sorting/__init__.py
thealgorithm/sorting/quick.py
thealgorithm-0.0.1a7.dist-info/LICENSE
thealgorithm-0.0.1a7.dist-info/METADATA
thealgorithm-0.0.1a7.dist-info/WHEEL
thealgorithm-0.0.1a7.dist-info/top_level.txt
thealgorithm-0.0.1a7.dist-info/RECORD
