Metadata-Version: 2.1
Name: thealgorithm
Version: 0.0.1a7
Summary: AppleBoiy's algorithm package
Home-page: https://github.com/AppleBoiy/algorithm
Author: AppleBoiy
Classifier: Programming Language :: Python :: 3
Classifier: License :: OSI Approved :: MIT License
Classifier: Operating System :: OS Independent
Requires-Python: >=3.6
License-File: LICENSE
